{
  "form": {
    "standard": {
      "bg-default": {
        "value": "{base.color.backdrop.standard.bgExtreme}",
        "type": "color"
      },
      "bg-alt": {
        "value": "{base.color.backdrop.standard.bgFirm}",
        "type": "color",
        "description": "progress bar bg, text editor preview and text editor footer"
      },
      "bg-disabled": {
        "value": "{base.color.selectable.inactive.defaultAlt}",
        "type": "color"
      },
      "bg-readOnly": {
        "value": "{base.color.selectable.inactive.defaultAlt}",
        "type": "color"
      },
      "border-default": {
        "value": "{base.color.backdrop.standard.bgFaint}",
        "type": "color"
      },
      "border-disabled": {
        "value": "{base.color.selectable.inactive.default}",
        "type": "color"
      },
      "border-readOnly": {
        "value": "{base.color.selectable.inactive.default}",
        "type": "color"
      },
      "icon-default": {
        "value": "{base.color.content.standard.fgFirm}",
        "type": "color"
      },
      "icon-disabled": {
        "value": "{base.color.selectable.inactive.default}",
        "type": "color"
      },
      "icon-readOnly": {
        "value": "{base.color.selectable.inactive.default}",
        "type": "color"
      },
      "text-default": {
        "value": "{base.color.content.standard.fgModerate}",
        "type": "color"
      },
      "text-disabled": {
        "value": "{base.color.selectable.inactive.content}",
        "type": "color"
      },
      "text-readOnly": {
        "value": "{base.color.content.standard.fgFirm}",
        "type": "color"
      }
    },
    "validation": {
      "border-error": {
        "value": "{base.color.status.negative.default}",
        "type": "color"
      },
      "bar-error": {
        "value": "{base.color.status.negative.default}",
        "type": "color",
        "description": "error bar to left of inputs"
      },
      "bar-warning": {
        "value": "{base.color.status.caution.default}",
        "type": "color",
        "description": "warning bar to left of inputs"
      },
      "label-error": {
        "value": "{base.color.status.negative.default}",
        "type": "color"
      },
      "label-warning": {
        "value": "{base.color.status.caution.default}",
        "type": "color"
      }
    },
    "labelset": {
      "label-required": {
        "value": "{base.color.selectable.danger.default}",
        "type": "color"
      },
      "label-default": {
        "value": "{base.color.content.standard.fgFirm}",
        "type": "color"
      },
      "label-alt": {
        "value": "{base.color.content.standard.fgModerate}",
        "type": "color",
        "description": "used for '(optional)' text and hint text."
      },
      "label-disabled": {
        "value": "{base.color.content.standard.fgDelicate}",
        "type": "color"
      },
      "label-readOnly": {
        "value": "{base.color.content.standard.fgFirm}",
        "type": "color"
      }
    }
  }
}