{
  "status": {
    "color": {
      "none": {
        "$type": "color",
        "$value": "{modes.color.none}",
        "$description": "transparent override used for hiding colors when needed."
      },
      "message": {
        "contextual": {
          "bg": {
            "$type": "color",
            "$value": "{modes.color.generic.bg.nought}"
          },
          "icon": {
            "$type": "color",
            "$value": "{modes.color.generic.bg.nought}",
            "$description": "decorative icon on standard contextual messages"
          },
          "icon-alt": {
            "$type": "color",
            "$value": "{modes.color.status.neutral.default}",
            "$description": "icon on neutral status dialogs"
          },
          "text": {
            "$type": "color",
            "$value": "{modes.color.status.content.withHoverAlt}",
            "$description": "Message text."
          },
          "AI": {
            "bg-default": {
              "$type": "color",
              "$value": "{modes.color.status.ai.defaultAlt}"
            },
            "bgAlt": {
              "$type": "color",
              "$value": "{modes.color.status.neutral.defaultAlt}"
            },
            "border-default": {
              "$type": "color",
              "$value": "{modes.color.status.ai.defaultAlt}"
            }
          },
          "callout": {
            "bgAlt": {
              "$type": "color",
              "$value": "{modes.color.status.callout.defaultAlt}",
              "$description": "Subtle message bg"
            },
            "icon": {
              "$type": "color",
              "$value": "{modes.color.status.content.withDefaultAlt}"
            }
          },
          "error": {
            "bg-default": {
              "$type": "color",
              "$value": "{modes.color.status.negative.default}"
            },
            "bgAlt": {
              "$type": "color",
              "$value": "{modes.color.status.negative.defaultAlt}",
              "$description": "Subtle message bg"
            },
            "border-default": {
              "$type": "color",
              "$value": "{modes.color.status.negative.default}"
            },
            "icon": {
              "$type": "color",
              "$value": "{modes.color.status.negative.default}",
              "$description": "Icon on tinted bgs"
            }
          },
          "info": {
            "bg-default": {
              "$type": "color",
              "$value": "{modes.color.status.info.default}"
            },
            "bgAlt": {
              "$type": "color",
              "$value": "{modes.color.status.info.defaultAlt}",
              "$description": "Subtle message bg"
            },
            "border-default": {
              "$type": "color",
              "$value": "{modes.color.status.info.default}"
            },
            "icon": {
              "$type": "color",
              "$value": "{modes.color.status.info.default}",
              "$description": "Icon on tinted bgs"
            }
          },
          "success": {
            "bg-default": {
              "$type": "color",
              "$value": "{modes.color.status.positive.default}"
            },
            "bgAlt": {
              "$type": "color",
              "$value": "{modes.color.status.positive.defaultAlt}",
              "$description": "Subtle message bg"
            },
            "border-default": {
              "$type": "color",
              "$value": "{modes.color.status.positive.default}"
            },
            "icon": {
              "$type": "color",
              "$value": "{modes.color.status.positive.default}",
              "$description": "Icon on tinted bgs"
            }
          },
          "warning": {
            "bg-default": {
              "$type": "color",
              "$value": "{modes.color.status.caution.default}"
            },
            "bgAlt": {
              "$type": "color",
              "$value": "{modes.color.status.caution.defaultAlt}",
              "$description": "Subtle message bg"
            },
            "border-default": {
              "$type": "color",
              "$value": "{modes.color.status.caution.default}"
            },
            "icon": {
              "$type": "color",
              "$value": "{modes.color.status.caution.default}",
              "$description": "Icon on tinted bgs"
            }
          }
        },
        "global": {
          "label-default": {
            "$type": "color",
            "$value": "{modes.color.status.content.withDefaultAlt}"
          },
          "label-hover": {
            "$type": "color",
            "$value": "{modes.color.interactive.monochrome.withHover}"
          },
          "callout": {
            "bg-default": {
              "$type": "color",
              "$value": "{modes.color.status.callout.defaultAlt}",
              "$description": "Global message bg"
            },
            "bg-hover": {
              "$type": "color",
              "$value": "{modes.color.status.callout.hoverAlt}",
              "$description": "global message bg hover"
            },
            "icon": {
              "$type": "color",
              "$value": "{modes.color.status.content.withDefaultAlt}",
              "$description": "Icon on tinted bgs"
            }
          },
          "info": {
            "bg-default": {
              "$type": "color",
              "$value": "{modes.color.status.info.defaultAlt}",
              "$description": "Global message bg"
            },
            "bg-hover": {
              "$type": "color",
              "$value": "{modes.color.status.info.hoverAlt}"
            },
            "icon": {
              "$type": "color",
              "$value": "{modes.color.status.info.default}",
              "$description": "Icon on tinted bgs"
            }
          },
          "warning": {
            "bg-default": {
              "$type": "color",
              "$value": "{modes.color.status.caution.defaultAlt}",
              "$description": "Global message bg"
            },
            "bg-hover": {
              "$type": "color",
              "$value": "{modes.color.status.caution.hoverAlt}"
            },
            "icon": {
              "$type": "color",
              "$value": "{modes.color.status.caution.default}",
              "$description": "Icon on tinted bgs"
            }
          }
        }
      },
      "pill": {
        "custom": {
          "blue": {
            "bg-default": {
              "$type": "color",
              "$value": "{modes.color.status.custom.blue.default}"
            },
            "bgAlt-default": {
              "$type": "color",
              "$value": "{modes.color.status.custom.blue.defaultAlt}",
              "$description": "outline pill bg"
            },
            "bgAlt-hover": {
              "$type": "color",
              "$value": "{modes.color.status.custom.blue.hoverAlt}"
            },
            "bg-hover": {
              "$type": "color",
              "$value": "{modes.color.status.custom.blue.hover}"
            },
            "border-default": {
              "$type": "color",
              "$value": "{modes.color.status.custom.blue.default}"
            }
          },
          "teal": {
            "bg-default": {
              "$type": "color",
              "$value": "{modes.color.status.custom.teal.default}"
            },
            "bgAlt-default": {
              "$type": "color",
              "$value": "{modes.color.status.custom.teal.defaultAlt}",
              "$description": "outline pill bg"
            },
            "bgAlt-hover": {
              "$type": "color",
              "$value": "{modes.color.status.custom.teal.hoverAlt}"
            },
            "bg-hover": {
              "$type": "color",
              "$value": "{modes.color.status.custom.teal.hover}"
            },
            "border-default": {
              "$type": "color",
              "$value": "{modes.color.status.custom.teal.default}"
            }
          },
          "green": {
            "bg-default": {
              "$type": "color",
              "$value": "{modes.color.status.custom.green.default}"
            },
            "bgAlt-default": {
              "$type": "color",
              "$value": "{modes.color.status.custom.green.defaultAlt}",
              "$description": "outline pill bg"
            },
            "bgAlt-hover": {
              "$type": "color",
              "$value": "{modes.color.status.custom.green.hoverAlt}"
            },
            "bg-hover": {
              "$type": "color",
              "$value": "{modes.color.status.custom.green.hover}"
            },
            "border-default": {
              "$type": "color",
              "$value": "{modes.color.status.custom.green.default}"
            }
          },
          "lime": {
            "bg-default": {
              "$type": "color",
              "$value": "{modes.color.status.custom.lime.default}"
            },
            "bgAlt-default": {
              "$type": "color",
              "$value": "{modes.color.status.custom.lime.defaultAlt}",
              "$description": "outline pill bg"
            },
            "bgAlt-hover": {
              "$type": "color",
              "$value": "{modes.color.status.custom.lime.hoverAlt}"
            },
            "bg-hover": {
              "$type": "color",
              "$value": "{modes.color.status.custom.lime.hover}"
            },
            "border-default": {
              "$type": "color",
              "$value": "{modes.color.status.custom.lime.default}"
            }
          },
          "orange": {
            "bg-default": {
              "$type": "color",
              "$value": "{modes.color.status.custom.orange.default}"
            },
            "bgAlt-default": {
              "$type": "color",
              "$value": "{modes.color.status.custom.orange.defaultAlt}",
              "$description": "outline pill bg"
            },
            "bgAlt-hover": {
              "$type": "color",
              "$value": "{modes.color.status.custom.orange.hoverAlt}"
            },
            "bg-hover": {
              "$type": "color",
              "$value": "{modes.color.status.custom.orange.hover}"
            },
            "border-default": {
              "$type": "color",
              "$value": "{modes.color.status.custom.orange.default}"
            }
          },
          "red": {
            "bg-default": {
              "$type": "color",
              "$value": "{modes.color.status.custom.red.default}"
            },
            "bgAlt-default": {
              "$type": "color",
              "$value": "{modes.color.status.custom.red.defaultAlt}",
              "$description": "outline pill bg"
            },
            "bgAlt-hover": {
              "$type": "color",
              "$value": "{modes.color.status.custom.red.hoverAlt}"
            },
            "bg-hover": {
              "$type": "color",
              "$value": "{modes.color.status.custom.red.hover}"
            },
            "border-default": {
              "$type": "color",
              "$value": "{modes.color.status.custom.red.default}"
            }
          },
          "pink": {
            "bg-default": {
              "$type": "color",
              "$value": "{modes.color.status.custom.pink.default}"
            },
            "bgAlt-default": {
              "$type": "color",
              "$value": "{modes.color.status.custom.pink.defaultAlt}",
              "$description": "outline pill bg"
            },
            "bgAlt-hover": {
              "$type": "color",
              "$value": "{modes.color.status.custom.pink.hoverAlt}"
            },
            "bg-hover": {
              "$type": "color",
              "$value": "{modes.color.status.custom.pink.hover}"
            },
            "border-default": {
              "$type": "color",
              "$value": "{modes.color.status.custom.pink.default}"
            }
          },
          "purple": {
            "bg-default": {
              "$type": "color",
              "$value": "{modes.color.status.custom.purple.default}"
            },
            "bgAlt-default": {
              "$type": "color",
              "$value": "{modes.color.status.custom.purple.defaultAlt}",
              "$description": "outline pill bg"
            },
            "bgAlt-hover": {
              "$type": "color",
              "$value": "{modes.color.status.custom.purple.hoverAlt}"
            },
            "bg-hover": {
              "$type": "color",
              "$value": "{modes.color.status.custom.purple.hover}"
            },
            "border-default": {
              "$type": "color",
              "$value": "{modes.color.status.custom.purple.default}"
            }
          },
          "gray": {
            "bg-default": {
              "$type": "color",
              "$value": "{modes.color.status.custom.gray.default}"
            },
            "bgAlt-default": {
              "$type": "color",
              "$value": "{modes.color.status.custom.gray.defaultAlt}",
              "$description": "outline pill bg"
            },
            "bgAlt-hover": {
              "$type": "color",
              "$value": "{modes.color.status.custom.gray.hoverAlt}"
            },
            "bg-hover": {
              "$type": "color",
              "$value": "{modes.color.status.custom.gray.hover}"
            },
            "border-default": {
              "$type": "color",
              "$value": "{modes.color.status.custom.gray.default}"
            }
          },
          "slate": {
            "bg-default": {
              "$type": "color",
              "$value": "{modes.color.status.custom.slate.default}"
            },
            "bgAlt-default": {
              "$type": "color",
              "$value": "{modes.color.status.custom.slate.defaultAlt}",
              "$description": "outline pill bg"
            },
            "bgAlt-hover": {
              "$type": "color",
              "$value": "{modes.color.status.custom.slate.hoverAlt}"
            },
            "bg-hover": {
              "$type": "color",
              "$value": "{modes.color.status.custom.slate.hover}"
            },
            "border-default": {
              "$type": "color",
              "$value": "{modes.color.status.custom.slate.default}"
            }
          }
        },
        "error": {
          "bg-default": {
            "$type": "color",
            "$value": "{modes.color.status.negative.default}"
          },
          "bgAlt-default": {
            "$type": "color",
            "$value": "{modes.color.status.negative.defaultAlt}",
            "$description": "outline pill bg"
          },
          "bgAlt-hover": {
            "$type": "color",
            "$value": "{modes.color.status.negative.hoverAlt}"
          },
          "bg-hover": {
            "$type": "color",
            "$value": "{modes.color.status.negative.hover}"
          },
          "border-default": {
            "$type": "color",
            "$value": "{modes.color.status.negative.default}"
          },
          "inverse": {
            "bg-default": {
              "$type": "color",
              "$value": "{modes.color.status.negative.inverse.default}"
            },
            "bgAlt-default": {
              "$type": "color",
              "$value": "{modes.color.status.negative.inverse.defaultAlt}",
              "$description": "outline pill bg"
            },
            "bgAlt-hover": {
              "$type": "color",
              "$value": "{modes.color.status.negative.inverse.hoverAlt}"
            },
            "bg-hover": {
              "$type": "color",
              "$value": "{modes.color.status.negative.inverse.hover}"
            },
            "border-default": {
              "$type": "color",
              "$value": "{modes.color.status.negative.inverse.default}"
            }
          }
        },
        "generic": {
          "label-default": {
            "$type": "color",
            "$value": "{modes.color.status.content.withDefault}"
          },
          "label-hover": {
            "$type": "color",
            "$value": "{modes.color.status.content.withHover}"
          },
          "labelAlt-default": {
            "$type": "color",
            "$value": "{modes.color.status.content.withDefaultAlt}"
          },
          "labelAlt-hover": {
            "$type": "color",
            "$value": "{modes.color.status.content.withDefaultAlt}"
          },
          "inverse": {
            "label-default": {
              "$type": "color",
              "$value": "{modes.color.status.content.inverse.withDefault}"
            },
            "label-hover": {
              "$type": "color",
              "$value": "{modes.color.status.content.inverse.withHover}"
            },
            "labelAlt-default": {
              "$type": "color",
              "$value": "{modes.color.status.content.inverse.withDefaultAlt}"
            },
            "labelAlt-hover": {
              "$type": "color",
              "$value": "{modes.color.status.content.inverse.withDefaultAlt}"
            }
          }
        },
        "important": {
          "bg-default": {
            "$type": "color",
            "$value": "{modes.color.status.important.default}"
          },
          "bgAlt-default": {
            "$type": "color",
            "$value": "{modes.color.status.important.defaultAlt}",
            "$description": "outline pill bg"
          },
          "bgAlt-hover": {
            "$type": "color",
            "$value": "{modes.color.status.important.hoverAlt}"
          },
          "bg-hover": {
            "$type": "color",
            "$value": "{modes.color.status.important.hover}"
          },
          "border-default": {
            "$type": "color",
            "$value": "{modes.color.status.important.default}"
          },
          "inverse": {
            "bg-default": {
              "$type": "color",
              "$value": "{modes.color.status.important.inverse.default}"
            },
            "bgAlt-default": {
              "$type": "color",
              "$value": "{modes.color.status.important.inverse.defaultAlt}",
              "$description": "outline pill bg"
            },
            "bgAlt-hover": {
              "$type": "color",
              "$value": "{modes.color.status.important.inverse.hoverAlt}"
            },
            "bg-hover": {
              "$type": "color",
              "$value": "{modes.color.status.important.inverse.hover}"
            },
            "border-default": {
              "$type": "color",
              "$value": "{modes.color.status.important.inverse.default}"
            }
          }
        },
        "info": {
          "bg-default": {
            "$type": "color",
            "$value": "{modes.color.status.info.default}"
          },
          "bgAlt-default": {
            "$type": "color",
            "$value": "{modes.color.status.info.defaultAlt}",
            "$description": "outline pill bg"
          },
          "bgAlt-hover": {
            "$type": "color",
            "$value": "{modes.color.status.info.hoverAlt}"
          },
          "bg-hover": {
            "$type": "color",
            "$value": "{modes.color.status.info.hover}"
          },
          "border-default": {
            "$type": "color",
            "$value": "{modes.color.status.info.default}"
          },
          "inverse": {
            "bg-default": {
              "$type": "color",
              "$value": "{modes.color.status.info.inverse.default}"
            },
            "bgAlt-default": {
              "$type": "color",
              "$value": "{modes.color.status.info.inverse.defaultAlt}",
              "$description": "outline pill bg"
            },
            "bgAlt-hover": {
              "$type": "color",
              "$value": "{modes.color.status.info.inverse.hoverAlt}"
            },
            "bg-hover": {
              "$type": "color",
              "$value": "{modes.color.status.info.inverse.hover}"
            },
            "border-default": {
              "$type": "color",
              "$value": "{modes.color.status.info.inverse.default}"
            }
          }
        },
        "neutral": {
          "bg-default": {
            "$type": "color",
            "$value": "{modes.color.status.neutral.default}"
          },
          "bgAlt-default": {
            "$type": "color",
            "$value": "{modes.color.status.neutral.defaultAlt}",
            "$description": "outline pill bg"
          },
          "bgAlt-hover": {
            "$type": "color",
            "$value": "{modes.color.status.neutral.hoverAlt}"
          },
          "bg-hover": {
            "$type": "color",
            "$value": "{modes.color.status.neutral.hover}"
          },
          "border-default": {
            "$type": "color",
            "$value": "{modes.color.status.neutral.default}"
          },
          "inverse": {
            "bg-default": {
              "$type": "color",
              "$value": "{modes.color.status.neutral.inverse.default}"
            },
            "bgAlt-default": {
              "$type": "color",
              "$value": "{modes.color.status.neutral.inverse.defaultAlt}",
              "$description": "outline pill bg"
            },
            "bgAlt-hover": {
              "$type": "color",
              "$value": "{modes.color.status.neutral.inverse.hoverAlt}"
            },
            "bg-hover": {
              "$type": "color",
              "$value": "{modes.color.status.neutral.inverse.hover}"
            },
            "border-default": {
              "$type": "color",
              "$value": "{modes.color.status.neutral.inverse.default}"
            }
          }
        },
        "readonly": {
          "bg-default": {
            "$type": "color",
            "$value": "{modes.color.status.inactive.default}",
            "$description": "Pill (all types, readonly, when nested in disabled parent components)"
          },
          "border-default": {
            "$type": "color",
            "$value": "{modes.color.status.inactive.default}",
            "$description": "Pill (all types, readonly, when nested in disabled parent components)"
          },
          "label": {
            "$type": "color",
            "$value": "{modes.color.generic.content.firm}",
            "$description": "Pill (all types, readonly, when nested in disabled parent components)"
          }
        },
        "success": {
          "bg-default": {
            "$type": "color",
            "$value": "{modes.color.status.positive.default}"
          },
          "bgAlt-default": {
            "$type": "color",
            "$value": "{modes.color.status.positive.defaultAlt}",
            "$description": "outline pill bg"
          },
          "bgAlt-hover": {
            "$type": "color",
            "$value": "{modes.color.status.positive.hoverAlt}"
          },
          "bg-hover": {
            "$type": "color",
            "$value": "{modes.color.status.positive.hover}"
          },
          "border-default": {
            "$type": "color",
            "$value": "{modes.color.status.positive.default}"
          },
          "inverse": {
            "bg-default": {
              "$type": "color",
              "$value": "{modes.color.status.positive.inverse.default}"
            },
            "bgAlt-default": {
              "$type": "color",
              "$value": "{modes.color.status.positive.inverse.defaultAlt}",
              "$description": "outline pill bg"
            },
            "bgAlt-hover": {
              "$type": "color",
              "$value": "{modes.color.status.positive.inverse.hoverAlt}"
            },
            "bg-hover": {
              "$type": "color",
              "$value": "{modes.color.status.positive.inverse.hover}"
            },
            "border-default": {
              "$type": "color",
              "$value": "{modes.color.status.positive.inverse.default}"
            }
          }
        },
        "warning": {
          "bg-default": {
            "$type": "color",
            "$value": "{modes.color.status.caution.default}"
          },
          "bgAlt-default": {
            "$type": "color",
            "$value": "{modes.color.status.caution.defaultAlt}",
            "$description": "Global message bg"
          },
          "bgAlt-hover": {
            "$type": "color",
            "$value": "{modes.color.status.caution.hoverAlt}"
          },
          "bg-hover": {
            "$type": "color",
            "$value": "{modes.color.status.caution.hover}"
          },
          "border-default": {
            "$type": "color",
            "$value": "{modes.color.status.caution.default}"
          },
          "inverse": {
            "bg-default": {
              "$type": "color",
              "$value": "{modes.color.status.caution.inverse.default}"
            },
            "bgAlt-default": {
              "$type": "color",
              "$value": "{modes.color.status.caution.inverse.defaultAlt}",
              "$description": "Global message bg"
            },
            "bgAlt-hover": {
              "$type": "color",
              "$value": "{modes.color.status.caution.inverse.hoverAlt}"
            },
            "bg-hover": {
              "$type": "color",
              "$value": "{modes.color.status.caution.inverse.hover}"
            },
            "border-default": {
              "$type": "color",
              "$value": "{modes.color.status.caution.inverse.default}"
            }
          }
        }
      },
      "rating": {
        "bg-default": {
          "$type": "color",
          "$value": "{modes.color.status.reviews.default}"
        },
        "bg-defaultAlt": {
          "$type": "color",
          "$value": "{modes.color.status.reviews.defaultAlt}"
        },
        "bg-hover": {
          "$type": "color",
          "$value": "{modes.color.status.reviews.hover}"
        },
        "border-default": {
          "$type": "color",
          "$value": "{modes.color.status.reviews.default}"
        }
      }
    },
    "size": {
      "pill": {
        "S": {
          "$type": "sizing",
          "$value": "{global.size.macro.XS} - {global.size.micro.XS}",
          "$description": "Min height"
        },
        "M": {
          "$type": "sizing",
          "$value": "{global.size.macro.XS}",
          "$description": "Min height and removable button."
        },
        "L": {
          "$type": "sizing",
          "$value": "{global.size.macro.XS} + {global.size.micro.XS}",
          "$description": "Min height and removable button"
        }
      },
      "message": {
        "statuscontainer": {
          "M": {
            "$type": "sizing",
            "$value": "{global.size.macro.S}",
            "$description": "message and toast icon container width"
          },
          "L": {
            "$type": "sizing",
            "$value": "{global.size.macro.M}",
            "$description": "message and toast icon container width"
          }
        },
        "messagecontent": {
          "maxwidth": {
            "$type": "sizing",
            "$value": "{container.size.responsive.XXXL}",
            "$description": "max width of content inside message to make sure there are roughly 12 works per line"
          }
        },
        "global": {
          "M": {
            "$type": "sizing",
            "$value": "{global.size.macro.M}",
            "$description": "Global message minheight"
          }
        }
      },
      "icon": {
        "M": {
          "$type": "sizing",
          "$value": "{global.size.icon.M}"
        }
      }
    },
    "radius": {
      "none": {
        "$type": "borderRadius",
        "$value": "{global.radius.none}",
        "$description": "Pill (embedded element inner corners)"
      },
      "message": {
        "$type": "borderRadius",
        "$value": "{global.radius.container.M}",
        "$description": "Message"
      },
      "pill": {
        "$type": "borderRadius",
        "$value": "{global.radius.container.SM}",
        "$description": "Pill (outer corners)"
      }
    },
    "space": {
      "none": {
        "$type": "spacing",
        "$value": "{global.space.none}"
      },
      "integral": {
        "x": {
          "$type": "spacing",
          "$value": "{global.space.micro.S}",
          "$description": "Space between pill label and icon. Space between message text and link."
        }
      },
      "pill": {
        "x": {
          "S": {
            "$type": "spacing",
            "$value": "{global.space.macro.XS} / 2"
          },
          "M": {
            "$type": "spacing",
            "$value": "{global.space.macro.XS} / 2"
          },
          "L": {
            "$type": "spacing",
            "$value": "{global.space.macro.XS} / 2"
          }
        }
      },
      "tooltip": {
        "x": {
          "$type": "spacing",
          "$value": "{global.space.micro.XXL}",
          "$description": "Right left padding. "
        },
        "y": {
          "$type": "spacing",
          "$value": "{global.space.micro.L}",
          "$description": "Top bottom padding. "
        }
      },
      "message": {
        "contextual": {
          "x": {
            "M": {
              "$type": "spacing",
              "$value": "{global.space.micro.XXL}",
              "$description": "Left and right padding on Medium message"
            },
            "L": {
              "$type": "spacing",
              "$value": "{global.space.macro.S}",
              "$description": "Left and right paddding on Large Message"
            }
          },
          "y": {
            "M": {
              "$type": "spacing",
              "$value": "{global.space.micro.XXL}",
              "$description": "Top and bottom padding on Medium message"
            },
            "L": {
              "$type": "spacing",
              "$value": "{global.space.macro.S}",
              "$description": "Top and bottom paddding on Large Message"
            }
          },
          "xg": {
            "M": {
              "$type": "spacing",
              "$value": "{global.space.micro.L}",
              "$description": "Gap between icon and text in subtle message, and between text and action button in typical message"
            },
            "L": {
              "$type": "spacing",
              "$value": "{global.space.macro.XS}",
              "$description": "Gap between icon and text in subtle message, and between text and action button in typical message"
            }
          },
          "yg": {
            "M": {
              "$type": "spacing",
              "$value": "{global.space.micro.XS}",
              "$description": "Gap between heading and other content"
            },
            "L": {
              "$type": "spacing",
              "$value": "{global.space.micro.S}",
              "$description": "Gap between heading and other content"
            }
          },
          "subtle": {
            "iconwrapper": {
              "y": {
                "M": {
                  "$type": "spacing",
                  "$value": "{global.space.micro.XS}",
                  "$description": "space above icon on subtle message for medium variant"
                },
                "L": {
                  "$type": "spacing",
                  "$value": "{global.space.micro.S}",
                  "$description": "space above icon on subtle message for large variant"
                }
              }
            }
          }
        },
        "global": {
          "x": {
            "M": {
              "$type": "spacing",
              "$value": "{global.space.macro.XL}",
              "$description": "Left and right padding on global message"
            }
          },
          "y": {
            "M": {
              "$type": "spacing",
              "$value": "{global.space.micro.L}",
              "$description": "Top and bottom padding on global message."
            }
          },
          "xg": {
            "M": {
              "$type": "spacing",
              "$value": "{global.space.macro.XS}",
              "$description": "Space between icon wrapper and text wrapper"
            }
          },
          "yg": {
            "M": {
              "$type": "spacing",
              "$value": "{global.space.micro.S}",
              "$description": "Gap between heading and other content."
            }
          },
          "CTA": {
            "Y": {
              "M": {
                "$type": "spacing",
                "$value": "{global.space.macro.XS}",
                "$description": "Top and bottom padding on global message for countdown"
              }
            },
            "yg": {
              "M": {
                "$type": "spacing",
                "$value": "{global.space.macro.M}",
                "$description": "Gap between countdown spacing for global message"
              }
            }
          },
          "iconwrapper": {
            "y": {
              "M": {
                "$type": "spacing",
                "$value": "{global.space.micro.XXL}",
                "$description": "Top padding on global message icon wrapper."
              }
            }
          }
        }
      }
    }
  }
}