{
  "table": {
    "color": {
      "header": {
        "subtle": {
          "bg-alt": {
            "value": "{base.color.generic.content.standard.extreme}",
            "type": "color",
            "$extensions": {
              "studio.tokens": {
                "modify": {
                  "type": "alpha",
                  "value": "0.08",
                  "space": "lch"
                }
              }
            },
            "description": "header alt"
          },
          "bg-default": {
            "value": "{origin.colors.transparent}",
            "type": "color"
          },
          "bg-hover": {
            "value": "{base.color.generic.content.standard.extreme}",
            "type": "color",
            "$extensions": {
              "studio.tokens": {
                "modify": {
                  "type": "alpha",
                  "value": "0.12",
                  "space": "lch"
                }
              }
            }
          },
          "border-default": {
            "value": "{base.color.generic.fg.standard.delicate}",
            "type": "color",
            "description": "Header borders"
          },
          "label-default": {
            "value": "{base.color.generic.content.standard.harsh}",
            "type": "color"
          },
          "label-hover": {
            "value": "{base.color.generic.content.standard.extreme}",
            "type": "color"
          }
        },
        "harsh": {
          "bg-alt": {
            "value": "{base.color.generic.bg.inverse.harsh}",
            "type": "color",
            "description": "Zebra stripes"
          },
          "bg-default": {
            "value": "{base.color.generic.bg.inverse.firm}",
            "type": "color"
          },
          "bg-hover": {
            "value": "{base.color.generic.bg.inverse.moderate}",
            "type": "color"
          },
          "border-default": {
            "value": "{base.color.generic.fg.inverse.moderate}",
            "type": "color"
          },
          "label-default": {
            "value": "{base.color.generic.content.inverse.harsh}",
            "type": "color"
          },
          "label-hover": {
            "value": "{base.color.generic.content.inverse.extreme}",
            "type": "color"
          }
        }
      },
      "row": {
        "bg-activated": {
          "value": "{base.color.interactive.primary.standard.default}",
          "type": "color"
        },
        "bg-active": {
          "value": "{base.color.interactive.monochrome.standard.active}",
          "type": "color"
        },
        "bg-default": {
          "value": "{base.color.generic.bg.standard.nought}",
          "type": "color"
        },
        "bg-alt": {
          "value": "{base.color.generic.bg.standard.delicate}",
          "type": "color",
          "description": "Zebra stripes"
        },
        "bg-alt2": {
          "value": "{base.color.generic.bg.standard.soft}",
          "type": "color",
          "description": "Zebra stripes + child items"
        },
        "bg-hover": {
          "value": "{base.color.generic.bg.standard.soft}",
          "type": "color"
        },
        "border-default": {
          "value": "{base.color.generic.fg.standard.delicate}",
          "type": "color"
        },
        "label-activated": {
          "value": "{base.color.generic.content.inverse.extreme}",
          "type": "color"
        },
        "label-active": {
          "value": "{base.color.generic.content.inverse.extreme}",
          "type": "color"
        },
        "label-default": {
          "value": "{base.color.generic.content.standard.harsh}",
          "type": "color"
        },
        "label-hover": {
          "value": "{base.color.generic.content.standard.extreme}",
          "type": "color"
        }
      },
      "footer": {
        "bg-default": {
          "value": "{base.color.generic.bg.standard.soft}",
          "type": "color"
        },
        "border-default": {
          "value": "{base.color.generic.fg.standard.delicate}",
          "type": "color",
          "description": "Header borders"
        },
        "label-default": {
          "value": "{base.color.interactive.monochrome.standard.default}",
          "type": "color"
        }
      }
    },
    "borderradius": {
      "container": {
        "value": "{global.borderradius.container.M}",
        "type": "borderRadius",
        "description": "Table (parent container)"
      }
    },
    "boxshadow": {
      "parentrow": {
        "value": "{global.box-shadow.container.far}",
        "type": "boxShadow"
      }
    },
    "borderwidth": {
      "thin": {
        "value": "{global.borderwidth.XS}",
        "type": "borderWidth",
        "description": "Table border"
      }
    },
    "space": {
      "none": {
        "value": "0",
        "type": "spacing"
      },
      "row": {
        "x": {
          "XS": {
            "value": "{global.space.micro.L}",
            "type": "spacing",
            "description": "Left and right padding inside XS row cells"
          },
          "S": {
            "value": "{global.space.macro.XS}",
            "type": "spacing",
            "description": "Left and right padding inside S row cells"
          },
          "M": {
            "value": "{global.space.macro.XS}",
            "type": "spacing",
            "description": "Left and right padding inside M row cells"
          },
          "L": {
            "value": "{global.space.macro.XS}",
            "type": "spacing",
            "description": "Left and right padding inside L row cells"
          },
          "XL": {
            "value": "{global.space.macro.XS}",
            "type": "spacing",
            "description": "Left and right padding inside XL row cells"
          }
        },
        "xg": {
          "XS": {
            "value": "{global.space.micro.L}",
            "type": "spacing",
            "description": "internal spacing between text, checkboxes, icons etc"
          },
          "S": {
            "value": "{global.space.micro.L}",
            "type": "spacing",
            "description": "internal spacing between text, checkboxes, icons etc"
          },
          "M": {
            "value": "{global.space.macro.XS}",
            "type": "spacing",
            "description": "internal spacing between text, checkboxes, icons etc"
          },
          "L": {
            "value": "{global.space.micro.L}",
            "type": "spacing",
            "description": "internal spacing between text, checkboxes, icons etc"
          },
          "XL": {
            "value": "{global.space.micro.L}",
            "type": "spacing",
            "description": "internal spacing between text, checkboxes, icons etc"
          }
        },
        "y": {
          "M": {
            "value": "{global.space.micro.L}",
            "type": "spacing",
            "description": "top and bottom adding inside pagination"
          }
        }
      },
      "rowchild": {
        "x": {
          "XS": {
            "value": "{global.space.macro.L} + {global.space.micro.S}",
            "type": "spacing",
            "description": "Left padding inside XS child row cells"
          },
          "S": {
            "value": "{global.space.macro.XL} + {global.space.micro.S}",
            "type": "spacing",
            "description": "Left padding inside S child row cells"
          },
          "M": {
            "value": "{global.space.macro.XL} + {global.space.micro.S}",
            "type": "spacing",
            "description": "Left padding inside M child row cells"
          },
          "L": {
            "value": "{global.space.macro.XL} + {global.space.micro.S}",
            "type": "spacing",
            "description": "Left padding inside L child row cells"
          },
          "XL": {
            "value": "{global.space.macro.XL} + {global.space.micro.S}",
            "type": "spacing",
            "description": "Left padding inside XL child row cells"
          }
        }
      }
    },
    "size": {
      "row": {
        "standard": {
          "XS": {
            "value": "{global.size.macro.XS}",
            "type": "sizing"
          },
          "S": {
            "value": "{global.size.macro.S}",
            "type": "sizing"
          },
          "M": {
            "value": "{global.size.macro.M}",
            "type": "sizing"
          },
          "L": {
            "value": "{global.size.macro.L}",
            "type": "sizing"
          },
          "XL": {
            "value": "{global.size.macro.XL} + {global.size.micro.M}",
            "type": "sizing"
          }
        },
        "doubleheight": {
          "XS": {
            "value": "{table.size.row.standard.XS} * 2",
            "type": "sizing"
          },
          "S": {
            "value": "{table.size.row.standard.S} * 2",
            "type": "sizing"
          },
          "M": {
            "value": "{table.size.row.standard.M} * 2",
            "type": "sizing"
          },
          "L": {
            "value": "{table.size.row.standard.L} * 2",
            "type": "sizing"
          },
          "XL": {
            "value": "{table.size.row.standard.XL} * 2",
            "type": "sizing"
          }
        }
      }
    }
  }
}